gwdg_idm_api/__init__.py
gwdg_idm_api/_version.py
gwdg_idm_api/base_models.py
gwdg_idm_api/core_models.py
gwdg_idm_api/string_cleaner.py
gwdg_idm_api/util.py
gwdg_idm_api/attributes/__init__.py
gwdg_idm_api/attributes/benutzerverwaltung.py
gwdg_idm_api/attributes/dynamischeexchangeverteiler.py
gwdg_idm_api/attributes/exchangeverteiler.py
gwdg_idm_api/attributes/gruppenverwaltung.py
gwdg_idm_api/attributes/ldapverteiler.py
gwdg_idm_api/attributes/mailinglisten.py
gwdg_idm_api/attributes/ressourcen.py
gwdg_idm_api/attributes/selfservice.py
gwdg_idm_api/attributes/sharedmailbox.py
gwdg_idm_api/create_templates/__init__.py
gwdg_idm_api/create_templates/benutzerverwaltung.py
gwdg_idm_api/create_templates/gruppenverwaltung.py
gwdg_idm_api/models/__init__.py
gwdg_idm_api/models/benutzerverwaltung.py
gwdg_idm_api/models/dynamischeexchangeverteiler.py
gwdg_idm_api/models/exchangeverteiler.py
gwdg_idm_api/models/gruppenverwaltung.py
gwdg_idm_api/models/ldapverteiler.py
gwdg_idm_api/models/mailinglisten.py
gwdg_idm_api/models/ressourcen.py
gwdg_idm_api/models/selfservice.py
gwdg_idm_api/models/sharedmailbox.py
gwdg_idm_api-3.0.2.dist-info/licenses/LICENSE
gwdg_idm_api-3.0.2.dist-info/METADATA
gwdg_idm_api-3.0.2.dist-info/WHEEL
gwdg_idm_api-3.0.2.dist-info/top_level.txt
gwdg_idm_api-3.0.2.dist-info/RECORD
