Metadata-Version: 2.4
Name: gwdg_idm_api
Version: 3.0.2
Summary: Interface to the GWDG IDM api
Home-page: https://gitlab.gwdg.de/mpi-dortmund/ze-edv-public/gwdg_idm_api
Author: Markus Stabrin
Author-email: markus.stabrin@mpi-dortmund.mpg.de
License: MIT
Classifier: License :: OSI Approved :: MIT License
Classifier: Programming Language :: Python :: 3
Classifier: Programming Language :: Python :: 3 :: Only
Requires-Python: >=3.10
License-File: LICENSE
Requires-Dist: pydantic
Requires-Dist: requests
Provides-Extra: dev
Requires-Dist: build; extra == "dev"
Requires-Dist: pre-commit; extra == "dev"
Requires-Dist: twine; extra == "dev"
Dynamic: license-file
